arjuna/__init__.py
arjuna/__main__.py
arjuna/main.py
arjuna/notes.txt
arjuna/configure/__init__.py
arjuna/configure/cli.py
arjuna/configure/configurator.py
arjuna/configure/options.py
arjuna/configure/stage.py
arjuna/configure/validator.py
arjuna/core/__init__.py
arjuna/core/checks.py
arjuna/core/constant.py
arjuna/core/discovery.py
arjuna/core/error.py
arjuna/core/fmt.py
arjuna/core/har.py
arjuna/core/importer.py
arjuna/core/utils.py
arjuna/core/value.py
arjuna/core/adv/__init__.py
arjuna/core/adv/decorators.py
arjuna/core/adv/proxy.py
arjuna/core/adv/py.py
arjuna/core/adv/wrappers.py
arjuna/core/db/__init__.py
arjuna/core/db/sqlite.py
arjuna/core/poller/__init__.py
arjuna/core/poller/caller.py
arjuna/core/poller/conditions.py
arjuna/core/reader/__init__.py
arjuna/core/reader/excel.py
arjuna/core/reader/hocon.py
arjuna/core/reader/ini.py
arjuna/core/thread/__init__.py
arjuna/core/thread/decorators.py
arjuna/core/types/__init__.py
arjuna/core/types/constants.py
arjuna/core/types/descriptors.py
arjuna/core/types/named_strings.py
arjuna/core/utils/__init__.py
arjuna/core/utils/cmd_utils.py
arjuna/core/utils/data_utils.py
arjuna/core/utils/exc_utils.py
arjuna/core/utils/file_utils.py
arjuna/core/utils/obj_utils.py
arjuna/core/utils/repr_utils.py
arjuna/core/utils/sys_utils.py
arjuna/core/utils/thread_utils.py
arjuna/core/writer/__init__.py
arjuna/core/writer/textfile.py
arjuna/drive/__init__.py
arjuna/drive/invoker/__init__.py
arjuna/drive/invoker/databroker.py
arjuna/engine/__init__.py
arjuna/engine/controller.py
arjuna/engine/logger.py
arjuna/engine/meta.py
arjuna/engine/pytest.py
arjuna/engine/pytestplug.py
arjuna/engine/track.py
arjuna/engine/data/__init__.py
arjuna/engine/data/factory.py
arjuna/engine/data/localizer.py
arjuna/engine/data/record.py
arjuna/engine/data/reference.py
arjuna/engine/data/source.py
arjuna/engine/data/store.py
arjuna/engine/data/entity/__init__.py
arjuna/engine/data/entity/address.py
arjuna/engine/data/entity/person.py
arjuna-1.2.24.dist-info/LICENSE.txt
arjuna-1.2.24.dist-info/METADATA
arjuna-1.2.24.dist-info/NOTICE.txt
arjuna-1.2.24.dist-info/WHEEL
arjuna-1.2.24.dist-info/entry_points.txt
arjuna-1.2.24.dist-info/top_level.txt
arjuna-1.2.24.dist-info/RECORD
