Metadata-Version: 2.1
Name: arjuna
Version: 1.2.24
Summary: Arjuna is a Python based test automation framework developed by Rahul Verma (www.rahulverma.net).
Home-page: https://rahulverma.net
Author: Rahul Verma
Author-email: 
License: Apache License, Version 2.0
Keywords: arjuna selenium testing automation page-object data-driven
Platform: UNKNOWN
Classifier: Environment :: Console
Classifier: Development Status :: 4 - Beta
Classifier: Intended Audience :: Developers
Classifier: Intended Audience :: Information Technology
Classifier: Topic :: Software Development :: Quality Assurance
Classifier: Topic :: Software Development :: Testing
Classifier: License :: OSI Approved :: Apache Software License
Classifier: Programming Language :: Python :: 3.5
Classifier: Programming Language :: Python :: 3 :: Only
Classifier: Programming Language :: Python :: Implementation :: CPython
Classifier: Operating System :: OS Independent
Classifier: Natural Language :: English
Requires-Dist: pyOpenSSL (>=0.14)
Requires-Dist: urllib3 (==1.25.3)
Requires-Dist: requests (==2.22.0)
Requires-Dist: lxml (==4.6.3)
Requires-Dist: requests-toolbelt (==0.9.1)
Requires-Dist: selenium (==4.0.0a7)
Requires-Dist: webdriver-manager (==3.2.2)
Requires-Dist: xlrd (==1.2.0)
Requires-Dist: xlwt (==1.3.0)
Requires-Dist: pyparsing (==2.4.0)
Requires-Dist: pyhocon (==0.3.51)
Requires-Dist: pytest (==6.2.1)
Requires-Dist: pytest-html (==2.1.1)
Requires-Dist: pytest-dependency (==0.4.0)
Requires-Dist: PyYAML (==6.0)
Requires-Dist: mimesis (==4.1.3)
Requires-Dist: jsonpath-rw (==1.4.0)
Requires-Dist: jsonpath-rw-ext (==1.2.2)
Requires-Dist: jsonpath-ng (==1.5.3)
Requires-Dist: genson (==1.2.1)
Requires-Dist: jsonschema (==3.2.0)
Requires-Dist: Pallets-Sphinx-Themes
Requires-Dist: oauthlib (==3.1.0)
Requires-Dist: requests-oauthlib (==1.3.0)
Requires-Dist: bs4 (==0.0.1)
Requires-Dist: browsermob-proxy (==0.8.0)
Requires-Dist: haralyzer (==1.8.0)
Requires-Dist: mysql-connector-python (==8.0.21)
